Metadata-Version: 2.1
Name: ahogeotagger
Version: 0.1.5
Summary: Rapidly search your text for large list of cities and countries
Home-page: https://github.com/ybashir/ahogeotagger
Author: Yasser Bashir
Author-email: yasser.bashir@arbisoft.com
License: UNKNOWN
Platform: UNKNOWN
Classifier: Programming Language :: Python :: 3
Classifier: License :: OSI Approved :: MIT License
Classifier: Operating System :: OS Independent
Requires-Python: >=3.6
